<?xml version="1.0"?>
<!--
    This file is part of brancher, a static site generation tool
    Copyright (C) 2015  Tyler Romeo <tylerromeo@gmail.com>

    This program is free software: you can redistribute it and/or modify
    it under the terms of the GNU General Public License as published by
    the Free Software Foundation, either version 3 of the License, or
    (at your option) any later version.

    This program is distributed in the hope that it will be useful,
    but WITHOUT ANY WARRANTY; without even the implied warranty of
    MERCHANTABILITY or FITNESS FOR A PARTICULAR PURPOSE.  See the
    GNU General Public License for more details.

    You should have received a copy of the GNU General Public License
    along with this program.  If not, see <http://www.gnu.org/licenses/>.
-->
<ruleset name="My first PHPMD rule set"
         xmlns="http://pmd.sf.net/ruleset/1.0.0"
         xmlns:xsi="http://www.w3.org/2001/XMLSchema-instance"
         xsi:schemaLocation="http://pmd.sf.net/ruleset/1.0.0 http://pmd.sf.net/ruleset_xml_schema.xsd"
         xsi:noNamespaceSchemaLocation="http://pmd.sf.net/ruleset_xml_schema.xsd">
    <description>
        Rules to check for castlepointanime/brancher
    </description>

    <rule ref="rulesets/codesize.xml/ExcessiveParameterList" />
    <rule ref="rulesets/controversial.xml" />
    <rule ref="rulesets/design.xml/ExitExpression" />
    <rule ref="rulesets/design.xml/EvalExpression" />
    <rule ref="rulesets/design.xml/GotoStatement" />
    <rule ref="rulesets/naming.xml" />
    <rule ref="rulesets/unusedcode.xml/UnusedPrivateField" />
    <rule ref="rulesets/unusedcode.xml/UnusedLocalVariable" />
    <rule ref="rulesets/unusedcode.xml/UnusedPrivateMethod" />
</ruleset>
